[
    {
        "propName": ".84 Acres \u00a0 Knoxville, Knox County, Tennessee $3,000",
        "agent": "",
        "description": "Big lot with green views. Almost an acre. Utilities should be at the street. Backs up to vacant land. This lot is in the city and will NOT take a mobile...\u00a0",
        "link": "/Knox-County-Tennessee-Land-for-sale/pid/3571993",
        "page": 1,
        "date": "04-14-2017",
        "pop": 850.5,
        "Parcels.Sum": 140.0,
        "State": "TN",
        "count": 1.0,
        "land": 508.0,
        "County": "Knox",
        "cid": 47093.0
    },
    {
        "propName": ".25 Acres \u00a0 Knoxville, Knox County, Tennessee $4,000",
        "agent": "",
        "description": "Beautiful rolling lot close to downtown on Historic Richmond Hill. Perfect location to build at a great price.\u00a0",
        "link": "/Knox-County-Tennessee-Land-for-sale/pid/4059864",
        "page": 1,
        "date": "04-14-2017",
        "pop": 850.5,
        "Parcels.Sum": 140.0,
        "State": "TN",
        "count": 1.0,
        "land": 508.0,
        "County": "Knox",
        "cid": 47093.0
    },
    {
        "propName": ".39 Acres \u00a0 Knoxville, Knox County, Tennessee $5,900",
        "agent": "",
        "description": "Great price for this building lot in Knoxville. Located on a good street about half a block off of Magnolia. Original owner paid $22,434 in 1989. Steeper...\u00a0",
        "link": "/Knox-County-Tennessee-Land-for-sale/pid/4058748",
        "page": 1,
        "date": "04-14-2017",
        "pop": 850.5,
        "Parcels.Sum": 140.0,
        "State": "TN",
        "count": 1.0,
        "land": 508.0,
        "County": "Knox",
        "cid": 47093.0
    },
    {
        "propName": ".3 Acres \u00a0 Knoxville, Knox County, Tennessee $9,000",
        "agent": "",
        "description": "This is a great lot to build on. It is currently zoned multi family 2-4 units. Seller says there is electric at the road, it has a water meter and sewer...\u00a0",
        "link": "/Knox-County-Tennessee-Land-for-sale/pid/27312527",
        "page": 1,
        "date": "04-14-2017",
        "pop": 850.5,
        "Parcels.Sum": 140.0,
        "State": "TN",
        "count": 1.0,
        "land": 508.0,
        "County": "Knox",
        "cid": 47093.0
    },
    {
        "propName": ".3 Acres \u00a0 Knoxville, Knox County, Tennessee $9,000",
        "agent": "",
        "description": "This is a great lot to build on. It is currently zoned for multi-family 2-4 units. Seller said electric at the road, it has a water meter and sewer is...\u00a0",
        "link": "/Knox-County-Tennessee-Land-for-sale/pid/27219077",
        "page": 1,
        "date": "04-14-2017",
        "pop": 850.5,
        "Parcels.Sum": 140.0,
        "State": "TN",
        "count": 1.0,
        "land": 508.0,
        "County": "Knox",
        "cid": 47093.0
    },
    {
        "propName": ".24 Acres \u00a0 Knoxville, Knox County, Tennessee $9,900",
        "agent": "",
        "description": "Build your dream home on this corner lot. Won't last long for this price.\u00a0",
        "link": "/Knox-County-Tennessee-Land-for-sale/pid/27623291",
        "page": 1,
        "date": "04-14-2017",
        "pop": 850.5,
        "Parcels.Sum": 140.0,
        "State": "TN",
        "count": 1.0,
        "land": 508.0,
        "County": "Knox",
        "cid": 47093.0
    },
    {
        "propName": ".24 Acres \u00a0 Knoxville, Knox County, Tennessee $9,900",
        "agent": "",
        "description": "Build your dream home on this corner lot. Won't last long for this price.\u00a0",
        "link": "/Knox-County-Tennessee-Land-for-sale/pid/27623535",
        "page": 1,
        "date": "04-14-2017",
        "pop": 850.5,
        "Parcels.Sum": 140.0,
        "State": "TN",
        "count": 1.0,
        "land": 508.0,
        "County": "Knox",
        "cid": 47093.0
    },
    {
        "propName": ".33 Acres \u00a0 Knoxville, Knox County, Tennessee $9,900",
        "agent": "",
        "description": "Wonderful lot in established neighborhood, to bring your plans and build a home of your dreams. At this price won't last long!!!\u00a0",
        "link": "/Knox-County-Tennessee-Land-for-sale/pid/27424085",
        "page": 1,
        "date": "04-14-2017",
        "pop": 850.5,
        "Parcels.Sum": 140.0,
        "State": "TN",
        "count": 1.0,
        "land": 508.0,
        "County": "Knox",
        "cid": 47093.0
    },
    {
        "propName": ".33 Acres \u00a0 Knoxville, Knox County, Tennessee $9,900",
        "agent": "",
        "description": "Wonderful lot in established neighborhood, to bring your plans and build a home of your dreams. At this price won't last long!!!\u00a0",
        "link": "/Knox-County-Tennessee-Land-for-sale/pid/27424347",
        "page": 1,
        "date": "04-14-2017",
        "pop": 850.5,
        "Parcels.Sum": 140.0,
        "State": "TN",
        "count": 1.0,
        "land": 508.0,
        "County": "Knox",
        "cid": 47093.0
    },
    {
        "propName": ".36 Acres \u00a0 Knoxville, Knox County, Tennessee $9,900",
        "agent": "Vanderbilt Mortgage And Finance, Inc.",
        "description": "HUGE REDUCTION!!!!.36 acre property located in Knoxville TN at 111 Stone Rd. Property sits road front and should have access to public utilities. contact today for more information or to make an offer. Feel free to visit the property anytime. No appointment required. ALL cash offers will be reviewed.\u00a0",
        "link": "/Knox-County-Tennessee-Land-for-sale/pid/25049297",
        "page": 1,
        "date": "04-14-2017",
        "pop": 850.5,
        "Parcels.Sum": 140.0,
        "State": "TN",
        "count": 1.0,
        "land": 508.0,
        "County": "Knox",
        "cid": 47093.0
    },
    {
        "propName": ".71 Acres \u00a0 Knoxville, Knox County, Tennessee $10,000",
        "agent": "",
        "description": "Almost 3/4 of a acre at an phenomenal price and great location. Ready for you to build your custom home, log home, or bring your mobile home. Surrounded...\u00a0",
        "link": "/Knox-County-Tennessee-Land-for-sale/pid/2875403",
        "page": 1,
        "date": "04-14-2017",
        "pop": 850.5,
        "Parcels.Sum": 140.0,
        "State": "TN",
        "count": 1.0,
        "land": 508.0,
        "County": "Knox",
        "cid": 47093.0
    },
    {
        "propName": ".25 Acres \u00a0 Knoxville, Knox County, Tennessee $12,000",
        "agent": "",
        "description": "Three lots available unrestricted on Rutledge Pike with electric and city water. Lot 3 is $15900; lot 2 is $12000, and lot 1 is $12000.\u00a0",
        "link": "/Knox-County-Tennessee-Land-for-sale/pid/3535205",
        "page": 1,
        "date": "04-14-2017",
        "pop": 850.5,
        "Parcels.Sum": 140.0,
        "State": "TN",
        "count": 1.0,
        "land": 508.0,
        "County": "Knox",
        "cid": 47093.0
    },
    {
        "propName": ".35 Acres \u00a0 Knoxville, Knox County, Tennessee $12,000",
        "agent": "",
        "description": "Three unrestricted lots available: wooded with city water and electric. Lot 3 is $15900; lot 2 is $12000 and lot 1 is $12000.\u00a0",
        "link": "/Knox-County-Tennessee-Land-for-sale/pid/3535203",
        "page": 1,
        "date": "04-14-2017",
        "pop": 850.5,
        "Parcels.Sum": 140.0,
        "State": "TN",
        "count": 1.0,
        "land": 508.0,
        "County": "Knox",
        "cid": 47093.0
    },
    {
        "propName": ".39 Acres \u00a0 Knoxville, Knox County, Tennessee $12,995",
        "agent": "",
        "description": "Go and show, Sign on Property. Restrictions and Plat attached\u00a0",
        "link": "/Knox-County-Tennessee-Land-for-sale/pid/27102089",
        "page": 1,
        "date": "04-14-2017",
        "pop": 850.5,
        "Parcels.Sum": 140.0,
        "State": "TN",
        "count": 1.0,
        "land": 508.0,
        "County": "Knox",
        "cid": 47093.0
    },
    {
        "propName": ".29 Acres \u00a0 Knoxville, Knox County, Tennessee $13,900",
        "agent": "",
        "description": "Two (2) city lot into one lot. Could be 2 lot again. Best Value. Great view, Good Area.\u00a0",
        "link": "/Knox-County-Tennessee-Land-for-sale/pid/299938186",
        "page": 1,
        "date": "04-14-2017",
        "pop": 850.5,
        "Parcels.Sum": 140.0,
        "State": "TN",
        "count": 1.0,
        "land": 508.0,
        "County": "Knox",
        "cid": 47093.0
    },
    {
        "propName": "1.2 Acres \u00a0 Knoxville, Knox County, Tennessee $14,900",
        "agent": "",
        "description": "Wooded ridge side makes for a dramatic setting. Yet so close to UT and downtown. Adjoining lots also for sale.\u00a0",
        "link": "/Knox-County-Tennessee-Land-for-sale/pid/27576010",
        "page": 2,
        "date": "04-14-2017",
        "pop": 850.5,
        "Parcels.Sum": 140.0,
        "State": "TN",
        "count": 1.0,
        "land": 508.0,
        "County": "Knox",
        "cid": 47093.0
    },
    {
        "propName": ".4 Acres \u00a0 Knoxville, Knox County, Tennessee $14,900",
        "agent": "",
        "description": "Nice lot 220+ feet deep. Knox Co. septic letter for 3 bedroom already on file.\u00a0",
        "link": "/Knox-County-Tennessee-Land-for-sale/pid/322269766",
        "page": 2,
        "date": "04-14-2017",
        "pop": 850.5,
        "Parcels.Sum": 140.0,
        "State": "TN",
        "count": 1.0,
        "land": 508.0,
        "County": "Knox",
        "cid": 47093.0
    },
    {
        "propName": ".41 Acres \u00a0 Knoxville, Knox County, Tennessee $15,000",
        "agent": "",
        "description": "Single family or multi family lot in convenient Knoxville location. Previous had a duplex on the property but has since been cleared. Front is level then...\u00a0",
        "link": "/Knox-County-Tennessee-Land-for-sale/pid/4058749",
        "page": 2,
        "date": "04-14-2017",
        "pop": 850.5,
        "Parcels.Sum": 140.0,
        "State": "TN",
        "count": 1.0,
        "land": 508.0,
        "County": "Knox",
        "cid": 47093.0
    },
    {
        "propName": ".75 Acres \u00a0 Corryton, Knox County, Tennessee $15,000",
        "agent": "",
        "description": "\u00a0",
        "link": "/Knox-County-Tennessee-Land-for-sale/pid/322066107",
        "page": 2,
        "date": "04-14-2017",
        "pop": 850.5,
        "Parcels.Sum": 140.0,
        "State": "TN",
        "count": 1.0,
        "land": 508.0,
        "County": "Knox",
        "cid": 47093.0
    },
    {
        "propName": "1.29 Acres \u00a0 Corryton, Knox County, Tennessee $15,000",
        "agent": "",
        "description": "\u00a0",
        "link": "/Knox-County-Tennessee-Land-for-sale/pid/322034449",
        "page": 2,
        "date": "04-14-2017",
        "pop": 850.5,
        "Parcels.Sum": 140.0,
        "State": "TN",
        "count": 1.0,
        "land": 508.0,
        "County": "Knox",
        "cid": 47093.0
    },
    {
        "propName": ".24 Acres \u00a0 Knoxville, Knox County, Tennessee $15,000",
        "agent": "",
        "description": "Best building lot left in Emory Vista with gorgeous Lake and Mountain views. Half of adjoining lot 79 may also be available.\u00a0",
        "link": "/Knox-County-Tennessee-Land-for-sale/pid/3040608",
        "page": 2,
        "date": "04-14-2017",
        "pop": 850.5,
        "Parcels.Sum": 140.0,
        "State": "TN",
        "count": 1.0,
        "land": 508.0,
        "County": "Knox",
        "cid": 47093.0
    },
    {
        "propName": ".41 Acres \u00a0 Knoxville, Knox County, Tennessee $15,000",
        "agent": "",
        "description": "Single family or multi family lot in convenient Knoxville location. Previous had a duplex on the property but has since been cleared. Front is level then...\u00a0",
        "link": "/Knox-County-Tennessee-Land-for-sale/pid/4059876",
        "page": 2,
        "date": "04-14-2017",
        "pop": 850.5,
        "Parcels.Sum": 140.0,
        "State": "TN",
        "count": 1.0,
        "land": 508.0,
        "County": "Knox",
        "cid": 47093.0
    },
    {
        "propName": ".24 Acres \u00a0 Knoxville, Knox County, Tennessee $15,000",
        "agent": "",
        "description": "Bordered on 3 sides by commercial properties, easily rezoned. See MLS 966431, right across street off Drinnen. Build on 1 lot, parking on the other, a...\u00a0",
        "link": "/Knox-County-Tennessee-Land-for-sale/pid/27814797",
        "page": 2,
        "date": "04-14-2017",
        "pop": 850.5,
        "Parcels.Sum": 140.0,
        "State": "TN",
        "count": 1.0,
        "land": 508.0,
        "County": "Knox",
        "cid": 47093.0
    },
    {
        "propName": "1.2 Acres \u00a0 Knoxville, Knox County, Tennessee $15,900",
        "agent": "",
        "description": "2 LOTS for 1 PRICE! Great convenient location with cul de sac lot privacy. Wooded & side by side.Size is approx. No survey on file.Wonderful size and...\u00a0",
        "link": "/Knox-County-Tennessee-Land-for-sale/pid/4056386",
        "page": 2,
        "date": "04-14-2017",
        "pop": 850.5,
        "Parcels.Sum": 140.0,
        "State": "TN",
        "count": 1.0,
        "land": 508.0,
        "County": "Knox",
        "cid": 47093.0
    },
    {
        "propName": ".5 Acres \u00a0 Knoxville, Knox County, Tennessee $15,900",
        "agent": "",
        "description": "Great building lot zoned agriculture - unrestricted with electric and city water. Three lots available: Lot 3 is $15900; lot 2 is $12000; and lot 1 is...\u00a0",
        "link": "/Knox-County-Tennessee-Land-for-sale/pid/3535202",
        "page": 2,
        "date": "04-14-2017",
        "pop": 850.5,
        "Parcels.Sum": 140.0,
        "State": "TN",
        "count": 1.0,
        "land": 508.0,
        "County": "Knox",
        "cid": 47093.0
    },
    {
        "propName": "1.12 Acres \u00a0 Knoxville, Knox County, Tennessee $17,900",
        "agent": "",
        "description": "Beautiful property, level lot. 1.12 acres, property is on both sides of the creek bed.\u00a0",
        "link": "/Knox-County-Tennessee-Land-for-sale/pid/3771219",
        "page": 2,
        "date": "04-14-2017",
        "pop": 850.5,
        "Parcels.Sum": 140.0,
        "State": "TN",
        "count": 1.0,
        "land": 508.0,
        "County": "Knox",
        "cid": 47093.0
    },
    {
        "propName": "1 Acre \u00a0 Knoxville, Knox County, Tennessee $18,000",
        "agent": "",
        "description": "High spot in the area possible cell tower location with updated zoning or residential\u00a0",
        "link": "/Knox-County-Tennessee-Land-for-sale/pid/2114647",
        "page": 2,
        "date": "04-14-2017",
        "pop": 850.5,
        "Parcels.Sum": 140.0,
        "State": "TN",
        "count": 1.0,
        "land": 508.0,
        "County": "Knox",
        "cid": 47093.0
    },
    {
        "propName": ".71 Acres \u00a0 Strawberry Plains, Knox County, Tennessee $18,000",
        "agent": "",
        "description": "Rolling wooded parcel of land located on quite Strawberry Plains county road. Conveniently located just 3 miles from Interstate 40 and less than 20...\u00a0",
        "link": "/Knox-County-Tennessee-Land-for-sale/pid/27123262",
        "page": 2,
        "date": "04-14-2017",
        "pop": 850.5,
        "Parcels.Sum": 140.0,
        "State": "TN",
        "count": 1.0,
        "land": 508.0,
        "County": "Knox",
        "cid": 47093.0
    },
    {
        "propName": ".6 Acres \u00a0 Knoxville, Knox County, Tennessee $18,000",
        "agent": "",
        "description": "Beautiful lot located in the cul-de-sac of an established neighborhood.\u00a0",
        "link": "/Knox-County-Tennessee-Land-for-sale/pid/27773290",
        "page": 2,
        "date": "04-14-2017",
        "pop": 850.5,
        "Parcels.Sum": 140.0,
        "State": "TN",
        "count": 1.0,
        "land": 508.0,
        "County": "Knox",
        "cid": 47093.0
    },
    {
        "propName": "3.15 Acres \u00a0 Powell, Knox County, Tennessee $19,000",
        "agent": "",
        "description": "One of the best values in upscale Arlington Ridge.Fantastic wooded estate home lots in Powell. High quality custom homes adorn this natural setting of...\u00a0",
        "link": "/Knox-County-Tennessee-Land-for-sale/pid/313092022",
        "page": 2,
        "date": "04-14-2017",
        "pop": 850.5,
        "Parcels.Sum": 140.0,
        "State": "TN",
        "count": 1.0,
        "land": 508.0,
        "County": "Knox",
        "cid": 47093.0
    },
    {
        "propName": ".99 Acres \u00a0 Knoxville, Knox County, Tennessee $19,900",
        "agent": "",
        "description": "Double lot in West Knoxville on a cul-de-sac. Quiet subdivision. Wooded. Each lot has been evaluated and is suitable for 2 bedroom septic. Schools are...\u00a0",
        "link": "/Knox-County-Tennessee-Land-for-sale/pid/2405491",
        "page": 3,
        "date": "04-14-2017",
        "pop": 850.5,
        "Parcels.Sum": 140.0,
        "State": "TN",
        "count": 1.0,
        "land": 508.0,
        "County": "Knox",
        "cid": 47093.0
    },
    {
        "propName": ".48 Acres \u00a0 Knoxville, Knox County, Tennessee $19,900",
        "agent": "",
        "description": "Build your dream house on a 0.43 acres. Close to Interstate, Broadway and shopping areas. Slightly rolling.\u00a0",
        "link": "/Knox-County-Tennessee-Land-for-sale/pid/27540098",
        "page": 3,
        "date": "04-14-2017",
        "pop": 850.5,
        "Parcels.Sum": 140.0,
        "State": "TN",
        "count": 1.0,
        "land": 508.0,
        "County": "Knox",
        "cid": 47093.0
    },
    {
        "propName": "2.33 Acres \u00a0 Knoxville, Knox County, Tennessee $19,900",
        "agent": "",
        "description": "Ideal location just off I-40 at Strawberry Plains. Unrestricted wooded acreage, and two adjoining tracts of 8.88 and 7.27 acres could be added for a total ...\u00a0",
        "link": "/Knox-County-Tennessee-Land-for-sale/pid/3191067",
        "page": 3,
        "date": "04-14-2017",
        "pop": 850.5,
        "Parcels.Sum": 140.0,
        "State": "TN",
        "count": 1.0,
        "land": 508.0,
        "County": "Knox",
        "cid": 47093.0
    },
    {
        "propName": "6.09 Acres \u00a0 Knoxville, Knox County, Tennessee $19,900",
        "agent": "",
        "description": "This property sits along I75 and Conner Rd. Mostly wooded with quite a bit of road frontage. You can be shopping and restaurants in minutes. Close to...\u00a0",
        "link": "/Knox-County-Tennessee-Land-for-sale/pid/325634765",
        "page": 3,
        "date": "04-14-2017",
        "pop": 850.5,
        "Parcels.Sum": 140.0,
        "State": "TN",
        "count": 1.0,
        "land": 508.0,
        "County": "Knox",
        "cid": 47093.0
    },
    {
        "propName": "6.09 Acres \u00a0 Powell, Knox County, Tennessee $19,900",
        "agent": "",
        "description": "For more information, contact Kim Pollard at (865) 924-0066. Visit http://www.crye-leike.com/smokymountains/200952 to view more pictures of this property. ...\u00a0",
        "link": "/Knox-County-Tennessee-Land-for-sale/pid/325682234",
        "page": 3,
        "date": "04-14-2017",
        "pop": 850.5,
        "Parcels.Sum": 140.0,
        "State": "TN",
        "count": 1.0,
        "land": 508.0,
        "County": "Knox",
        "cid": 47093.0
    },
    {
        "propName": "6.09 Acres \u00a0 Powell, Knox County, Tennessee $19,900",
        "agent": "",
        "description": "For more information, contact Kim Pollard at (865) 924-0066. Visit http://www.crye-leike.com/knoxville/901547 to view more pictures of this property. This ...\u00a0",
        "link": "/Knox-County-Tennessee-Land-for-sale/pid/307459247",
        "page": 3,
        "date": "04-14-2017",
        "pop": 850.5,
        "Parcels.Sum": 140.0,
        "State": "TN",
        "count": 1.0,
        "land": 508.0,
        "County": "Knox",
        "cid": 47093.0
    },
    {
        "propName": "1.91 Acres \u00a0 Powell, Knox County, Tennessee $20,000",
        "agent": "",
        "description": "Almost 2 Acres at the entrance to Thornbrook Subdivision, great area, in FEMA Flood Zone AE...Bank owned, will consider all offers!\u00a0",
        "link": "/Knox-County-Tennessee-Land-for-sale/pid/27784932",
        "page": 3,
        "date": "04-14-2017",
        "pop": 850.5,
        "Parcels.Sum": 140.0,
        "State": "TN",
        "count": 1.0,
        "land": 508.0,
        "County": "Knox",
        "cid": 47093.0
    },
    {
        "propName": ".61 Acres \u00a0 Corryton, Knox County, Tennessee $22,500",
        "agent": "",
        "description": "\u00a0",
        "link": "/Knox-County-Tennessee-Land-for-sale/pid/322066121",
        "page": 3,
        "date": "04-14-2017",
        "pop": 850.5,
        "Parcels.Sum": 140.0,
        "State": "TN",
        "count": 1.0,
        "land": 508.0,
        "County": "Knox",
        "cid": 47093.0
    },
    {
        "propName": "1.89 Acres \u00a0 Powell, Knox County, Tennessee $24,900",
        "agent": "",
        "description": "Nice lot for home or recreation.\u00a0",
        "link": "/Knox-County-Tennessee-Land-for-sale/pid/3807803",
        "page": 3,
        "date": "04-14-2017",
        "pop": 850.5,
        "Parcels.Sum": 140.0,
        "State": "TN",
        "count": 1.0,
        "land": 508.0,
        "County": "Knox",
        "cid": 47093.0
    },
    {
        "propName": "1.03 Acres \u00a0 Knoxville, Knox County, Tennessee $24,900",
        "agent": "",
        "description": "Nice lots for building homes with a possible basement. Nice size wooded lots with privacy. Great neighborhood with mountain views. Perfect lot to build...\u00a0",
        "link": "/Knox-County-Tennessee-Land-for-sale/pid/312115993",
        "page": 3,
        "date": "04-14-2017",
        "pop": 850.5,
        "Parcels.Sum": 140.0,
        "State": "TN",
        "count": 1.0,
        "land": 508.0,
        "County": "Knox",
        "cid": 47093.0
    },
    {
        "propName": "4.3 Acres \u00a0 Knoxville, Knox County, Tennessee $24,900",
        "agent": "",
        "description": "Long tract, close-in South. Would make good homestead. Remnants of barn may still be visible. Near Charter Doyle Dog Park. Needs some clearing for an...\u00a0",
        "link": "/Knox-County-Tennessee-Land-for-sale/pid/3592637",
        "page": 3,
        "date": "04-14-2017",
        "pop": 850.5,
        "Parcels.Sum": 140.0,
        "State": "TN",
        "count": 1.0,
        "land": 508.0,
        "County": "Knox",
        "cid": 47093.0
    },
    {
        "propName": ".3 Acres \u00a0 Knoxville, Knox County, Tennessee $24,900",
        "agent": "",
        "description": "Great restricted neighborhood. Sewer and water available. Minimum build 1500 SF, 2 car attached garage.\u00a0",
        "link": "/Knox-County-Tennessee-Land-for-sale/pid/3093414",
        "page": 3,
        "date": "04-14-2017",
        "pop": 850.5,
        "Parcels.Sum": 140.0,
        "State": "TN",
        "count": 1.0,
        "land": 508.0,
        "County": "Knox",
        "cid": 47093.0
    },
    {
        "propName": "4.25 Acres \u00a0 Knoxville, Knox County, Tennessee $24,900",
        "agent": "",
        "description": "Great corner lot with commercial potential. Road frontage on Hwy 33 / Maynardville Hwy.\u00a0",
        "link": "/Knox-County-Tennessee-Land-for-sale/pid/326038051",
        "page": 3,
        "date": "04-14-2017",
        "pop": 850.5,
        "Parcels.Sum": 140.0,
        "State": "TN",
        "count": 1.0,
        "land": 508.0,
        "County": "Knox",
        "cid": 47093.0
    },
    {
        "propName": ".3 Acres \u00a0 Knoxville, Knox County, Tennessee $24,900",
        "agent": "",
        "description": "Great restricted neighborhood, sewer and water available. Minimum 1500 SF build, 2 car attached garage.\u00a0",
        "link": "/Knox-County-Tennessee-Land-for-sale/pid/2948212",
        "page": 3,
        "date": "04-14-2017",
        "pop": 850.5,
        "Parcels.Sum": 140.0,
        "State": "TN",
        "count": 1.0,
        "land": 508.0,
        "County": "Knox",
        "cid": 47093.0
    },
    {
        "propName": "1.03 Acres \u00a0 Knoxville, Knox County, Tennessee $24,900",
        "agent": "",
        "description": "Great building lot for your Dream Home. Ridge Top Sub with Mountain Views. Nice lot for any home style including a basement plan. Lot is priced in a range ...\u00a0",
        "link": "/Knox-County-Tennessee-Land-for-sale/pid/312115991",
        "page": 3,
        "date": "04-14-2017",
        "pop": 850.5,
        "Parcels.Sum": 140.0,
        "State": "TN",
        "count": 1.0,
        "land": 508.0,
        "County": "Knox",
        "cid": 47093.0
    },
    {
        "propName": ".3 Acres \u00a0 Knoxville, Knox County, Tennessee $24,900",
        "agent": "",
        "description": "Great restricted neighborhood. Sewer and water available. Minimum build 1500 SF, 2 car attached garage.\u00a0",
        "link": "/Knox-County-Tennessee-Land-for-sale/pid/3093414",
        "page": 4,
        "date": "04-14-2017",
        "pop": 850.5,
        "Parcels.Sum": 140.0,
        "State": "TN",
        "count": 1.0,
        "land": 508.0,
        "County": "Knox",
        "cid": 47093.0
    },
    {
        "propName": "4.25 Acres \u00a0 Knoxville, Knox County, Tennessee $24,900",
        "agent": "",
        "description": "Great corner lot with commercial potential. Road frontage on Hwy 33 / Maynardville Hwy.\u00a0",
        "link": "/Knox-County-Tennessee-Land-for-sale/pid/326038051",
        "page": 4,
        "date": "04-14-2017",
        "pop": 850.5,
        "Parcels.Sum": 140.0,
        "State": "TN",
        "count": 1.0,
        "land": 508.0,
        "County": "Knox",
        "cid": 47093.0
    },
    {
        "propName": "1.03 Acres \u00a0 Knoxville, Knox County, Tennessee $24,900",
        "agent": "",
        "description": "Great building lot for your Dream Home. Ridge Top Sub with Mountain Views. Nice lot for any home style including a basement plan. Lot is priced in a range ...\u00a0",
        "link": "/Knox-County-Tennessee-Land-for-sale/pid/312115991",
        "page": 4,
        "date": "04-14-2017",
        "pop": 850.5,
        "Parcels.Sum": 140.0,
        "State": "TN",
        "count": 1.0,
        "land": 508.0,
        "County": "Knox",
        "cid": 47093.0
    },
    {
        "propName": "2 Acres \u00a0 Knoxville, Knox County, Tennessee $25,000",
        "agent": "",
        "description": "Great building site for your next home. Private and wooded 2 Acre lot is only 14 minutes from downtown Knoxville.\u00a0",
        "link": "/Knox-County-Tennessee-Land-for-sale/pid/2653397",
        "page": 4,
        "date": "04-14-2017",
        "pop": 850.5,
        "Parcels.Sum": 140.0,
        "State": "TN",
        "count": 1.0,
        "land": 508.0,
        "County": "Knox",
        "cid": 47093.0
    },
    {
        "propName": "1.22 Acres \u00a0 Knoxville, Knox County, Tennessee $25,000",
        "agent": "",
        "description": "In the heart of the Ramsey Community! This area of older homes makes you feel like you have stepped into Mayberry! The older cottages have big front...\u00a0",
        "link": "/Knox-County-Tennessee-Land-for-sale/pid/3993438",
        "page": 4,
        "date": "04-14-2017",
        "pop": 850.5,
        "Parcels.Sum": 140.0,
        "State": "TN",
        "count": 1.0,
        "land": 508.0,
        "County": "Knox",
        "cid": 47093.0
    },
    {
        "propName": ".56 Acres \u00a0 Knoxville, Knox County, Tennessee $25,000",
        "agent": "",
        "description": "Water, electricity, cable, gas and sewer available.Flat, cleared lot. Zoned O. Can be used for residential too.Owner financing with $10,000 down, 5% APR,...\u00a0",
        "link": "/Knox-County-Tennessee-Land-for-sale/pid/2429034",
        "page": 4,
        "date": "04-14-2017",
        "pop": 850.5,
        "Parcels.Sum": 140.0,
        "State": "TN",
        "count": 1.0,
        "land": 508.0,
        "County": "Knox",
        "cid": 47093.0
    },
    {
        "propName": "1 Acre \u00a0 Knoxville, Knox County, Tennessee $25,000",
        "agent": "",
        "description": "Creek front on quite road, country setting with great views.\u00a0",
        "link": "/Knox-County-Tennessee-Land-for-sale/pid/27940745",
        "page": 4,
        "date": "04-14-2017",
        "pop": 850.5,
        "Parcels.Sum": 140.0,
        "State": "TN",
        "count": 1.0,
        "land": 508.0,
        "County": "Knox",
        "cid": 47093.0
    },
    {
        "propName": "1.15 Acres \u00a0 Knoxville, Knox County, Tennessee $25,000",
        "agent": "",
        "description": "\u00a0",
        "link": "/Knox-County-Tennessee-Land-for-sale/pid/27560898",
        "page": 4,
        "date": "04-14-2017",
        "pop": 850.5,
        "Parcels.Sum": 140.0,
        "State": "TN",
        "count": 1.0,
        "land": 508.0,
        "County": "Knox",
        "cid": 47093.0
    }
]