[
    {
        "propName": ".21 Acres \u00a0 Colorado City, Mitchell County, Texas $5,000",
        "agent": "",
        "description": "Nice neighborhood to build a home or have one moved in. Not zoned for mobile homes but okay for modular or redi-built homes.\u00a0",
        "link": "/Mitchell-County-Texas-Land-for-sale/pid/2580671",
        "page": 1,
        "date": "04-14-2017",
        "pop": 10.3,
        "Parcels.Sum": 27.0,
        "State": "TX",
        "count": 4.0,
        "land": 911.0,
        "County": "Mitchell",
        "cid": 48335.0
    },
    {
        "propName": ".36 Acres \u00a0 Colorado City, Mitchell County, Texas $11,000",
        "agent": "",
        "description": "Large waterfront lot on LCR 252. Has burned cabin on site.. Owner/Listing agent is a Licensed Texas Realtor. Has utilities including septic tank.\u00a0",
        "link": "/Mitchell-County-Texas-Land-for-sale/pid/27013513",
        "page": 1,
        "date": "04-14-2017",
        "pop": 10.3,
        "Parcels.Sum": 27.0,
        "State": "TX",
        "count": 4.0,
        "land": 911.0,
        "County": "Mitchell",
        "cid": 48335.0
    },
    {
        "propName": "2.1 Acres \u00a0 Colorado City, Mitchell County, Texas $12,500",
        "agent": "",
        "description": "2 acres ready to build. Previous structures have been removed. Contact us for more information.\u00a0",
        "link": "/Mitchell-County-Texas-Land-for-sale/pid/313928865",
        "page": 1,
        "date": "04-14-2017",
        "pop": 10.3,
        "Parcels.Sum": 27.0,
        "State": "TX",
        "count": 4.0,
        "land": 911.0,
        "County": "Mitchell",
        "cid": 48335.0
    }
]