[
    {
        "propName": "1.07 Acres \u00a0 Dolan Springs, Mohave County, Arizona $5,900",
        "agent": "Richard Yukes",
        "description": "",
        "link": "/Mohave-County-Arizona-Land-for-sale/pid/25057417",
        "page": 1,
        "date": "04-14-2017",
        "pop": 247.3,
        "Parcels.Sum": 82.0,
        "State": "NV",
        "count": 5.0,
        "land": 7891.0,
        "County": "City Of Henderson \u2013 Clark",
        "cid": 32003.0
    },
    {
        "propName": "5 Acres \u00a0 Dolan Springs, Mohave County, Arizona $14,800",
        "agent": "Richard Yukes",
        "description": "",
        "link": "/Mohave-County-Arizona-Land-for-sale/pid/25056272",
        "page": 1,
        "date": "04-14-2017",
        "pop": 247.3,
        "Parcels.Sum": 82.0,
        "State": "NV",
        "count": 5.0,
        "land": 7891.0,
        "County": "City Of Henderson \u2013 Clark",
        "cid": 32003.0
    },
    {
        "propName": "5 Acres \u00a0 Dolan Springs, Mohave County, Arizona $17,400",
        "agent": "Richard Yukes",
        "description": "Price: $17,400 351-04-037B Terms: $500 down, $213.95 per month for 86 months at 5%, No Credit check.. No paperwork fees. All of your money goes to work. Parcel Size: 5 acres, Parcel Dimensions: 330 feet x 660 feetElevation 2960 feetFrontage: SE Corner of W Spiegel Ave and North Agua Dulce Drive No HOA fees2016 Annual Real Estate Tax: $ 103.06Free...\u00a0",
        "link": "/Mohave-County-Arizona-Land-for-sale/pid/25044936",
        "page": 1,
        "date": "04-14-2017",
        "pop": 247.3,
        "Parcels.Sum": 82.0,
        "State": "NV",
        "count": 5.0,
        "land": 7891.0,
        "County": "City Of Henderson \u2013 Clark",
        "cid": 32003.0
    }
]